Workbook

Sheet Costs & Prices
A1: MODULES
A2: Name | B2: Cost | C2: Watts | D2: DC Qual?
A3: Hyundai 440W (Black) | B3: 305 | C3: 440 | D3: No
A4: Silfab 440W (Black/Gold) | B4: 305 | C4: 440 | D4: No
A5: Silfab 430W (Black/Gold) | B5: 300 | C5: 430 | D5: No
A7: INVERTERS
A8: Name | B8: Cost
A9: Tesla 7.6kW Inverter | B9: 1200
A10: Tesla 5.0kW Inverter | B10: 1200
A11: Tesla 3.8kW Inverter | B11: 1200
A12: Enphase IQ8MC Micro | B12: 160
A13: Enphase IQ8X Micro | B13: 158
A14: Enphase IQ8A Micro | B14: 143
A15: Enphase IQ8M Micro | B15: 150
A17: BATTERIES
A18: Name | B18: Cost | C18: Labour | D18: DC Qual?
A19: Tesla Powerwall 3 | B19: 7700 | C19: 2600 | D19: Yes
A20: PW3 Expansion Pack | B20: 5000 | C20: 1900 | D20: Yes
A22: OTHER EQUIPMENT
A23: Name | B23: Cost | C23: Bundled?
A24: Tesla Wall Connector (Gen 3) | B24: 600 | C24: No
A25: Tesla Backup Switch | B25: 305 | C25: Yes
A27: PRICING SCHEMES
A28: Scheme | B28: Markup %
A29: Base (Colorado) | B29: 0.4
A30: Ventura | B30: 0.36
A31: Bay Area | B31: 0.5
A32: D&R | B32: 0.3
A33: Off Grid Homes | B33: 0.65
A35: ROOF TYPES
A36: Type | B36: Fixed ($) | C36: Per-Watt ($)
A37: Comp/Asphalt Shingle | B37: 0 | C37: 0
A38: Flat Membrane | B38: 0 | C38: 0.35
A39: Tile Concrete | B39: 3500 | C39: 0.8
A40: Wood Shake | B40: 0 | C40: 0.35
A41: Metal Corrugated | B41: 0 | C41: 0.35
A43: STOREY ADDERS
A44: Stories | B44: Per-Watt ($)
A45: 1 Story | B45: 0
A46: 2 Stories | B46: 0.05
A47: 3+ Stories | B47: 0.83
A49: PITCH ADDERS
A50: Slope | B50: Per-Watt ($)
A51: Standard (< 34°) | B51: 0
A52: Steep (34°-44°) | B52: 0.35
A53: Very Steep (> 44°) | B53: 0.5
A55: COST SCHEME RATES
A56: Item | B56: Rate | C56: Unit
A57: Racking | B57: 0.15 | C57: $/W
A58: BOS | B58: 0.15 | C58: $/W
A59: Labour | B59: 0.55 | C59: $/W
A60: Lead Gen (fixed) | B60: 300 | C60: $/system
A61: Lead Gen (per-watt) | B61: 0.1 | C61: $/W
A62: Salary | B62: 100 | C62: $/system
A63: Commission | B63: 0.05 | C63: % of COGS+Labour
A64: Pre-sale | B64: 0.01 | C64: $/W
A65: PM | B65: 1000 | C65: $/system
A66: Design | B66: 350 | C66: $/system
A67: Permit | B67: 500 | C67: $/system
A68: Battery Misc | B68: 200 | C68: $/system
A70: PE LEASE PARAMETERS
A71: Parameter | B71: Value | C71: Notes
A72: Baseline Factor | B72: 1.4285714 | C72: 10/7 per PE Pricing Policy v3
A73: DC Bonus | B73: 0.1098901 | C73: When domestic content qualifies
A74: No Bonus Penalty | B74: -0.0952381 | C74: No DC and no Energy Community
A75: Customer Discount | B75: 0.3 | C75: PE customer pays 70%

Sheet Calculator
A1: PB Pricing Calculator
A3: EQUIPMENT
B4: Selection | C4: Qty | D4: Cost/Unit | E4: Total
A5: Module | B5: Hyundai 440W (Black) | C5: 0 | D5: =VLOOKUP(B5,'Costs & Prices'!A3:B5,2,FALSE()) -> 305 | E5: =C5*D5 -> 0 | F5: =VLOOKUP(B5,'Costs & Prices'!A3:C5,3,FALSE()) -> 440
A6: Module 2 (optional) | B6: (none) | C6: 0 | D6: =IF(B6="(none)",0,VLOOKUP(B6,'Costs & Prices'!A3:B5,2,FALSE())) -> 0 | E6: =C6*D6 -> 0 | F6: =IF(B6="(none)",0,VLOOKUP(B6,'Costs & Prices'!A3:C5,3,FALSE())) -> 0
A7: Inverter | B7: Tesla 7.6kW Inverter | C7: 0 | D7: =VLOOKUP(B7,'Costs & Prices'!A9:B15,2,FALSE()) -> 1200 | E7: =C7*D7 -> 0
A8: Inverter 2 (optional) | B8: (none) | C8: 0 | D8: =IF(B8="(none)",0,VLOOKUP(B8,'Costs & Prices'!A9:B15,2,FALSE())) -> 0 | E8: =C8*D8 -> 0
A9: Battery | B9: (none) | C9: 0 | D9: =IF(B9="(none)",0,VLOOKUP(B9,'Costs & Prices'!A19:B20,2,FALSE())) -> 0 | E9: =C9*D9 -> 0 | F9: =IF(B9="(none)",0,VLOOKUP(B9,'Costs & Prices'!A19:C20,3,FALSE())) -> 0
A10: Battery 2 (optional) | B10: (none) | C10: 0 | D10: =IF(B10="(none)",0,VLOOKUP(B10,'Costs & Prices'!A19:B20,2,FALSE())) -> 0 | E10: =C10*D10 -> 0 | F10: =IF(B10="(none)",0,VLOOKUP(B10,'Costs & Prices'!A19:C20,3,FALSE())) -> 0
A11: EV Charger | B11: No | C11: 1 | D11: ='Costs & Prices'!B24 -> 600 | E11: =IF(B11="Yes",C11*D11,0) -> 0
A13: CONFIGURATION
A14: Pricing Scheme | B14: Base (Colorado) | C14: Markup: | D14: =VLOOKUP(B14,'Costs & Prices'!A29:B33,2,FALSE()) -> 0.4
A15: Roof Type | B15: Comp/Asphalt Shingle | C15: Fixed: | D15: =VLOOKUP(B15,'Costs & Prices'!A37:C41,2,FALSE()) -> 0 | E15: =VLOOKUP(B15,'Costs & Prices'!A37:C41,3,FALSE()) -> 0
A16: Storey | B16: 1 Story | C16: $/W: | D16: =VLOOKUP(B16,'Costs & Prices'!A45:B47,2,FALSE()) -> 0
A17: Roof Pitch | B17: Standard (< 34°) | C17: $/W: | D17: =VLOOKUP(B17,'Costs & Prices'!A51:B53,2,FALSE()) -> 0
A18: PE Deal? | B18: No
A19: Energy Community? | B19: No
A20: Custom Adder ($) | B20: 0 | C20: e.g. -1000 promo
A22: SYSTEM SUMMARY
A23: Total Panels | B23: =C5+C6 -> 0
A24: Total Watts | B24: =C5*F5+C6*F6 -> 0 | C24: =B24/1000 -> 0 | D24: kW DC
A25: Total Batteries | B25: =C9+C10 -> 0
A26: Battery Only? | B26: =IF(AND(B23=0,B25>0),"Yes","No") -> No
A28: COST BREAKDOWN
A29: Module Cost | E29: =E5+E6 -> 0
A30: Inverter Cost | E30: =E7+E8 -> 0
A31: Battery Cost | E31: =E9+E10 -> 0
A32: Other Equipment | E32: =E11 -> 0
A33: Battery Misc | E33: =IF(OR(B26="Yes",B25>=2),IF(B25>0,'Costs & Prices'!B68,0),0) -> 0
A34: Racking | E34: =B24*'Costs & Prices'!B57 -> 0
A35: BOS | E35: =B24*'Costs & Prices'!B58 -> 0
A36: COGS | E36: =SUM(E29:E35) -> 0
A38: Roof Adder | E38: =D15+B24*E15 -> 0
A39: Storey Adder | E39: =B24*D16 -> 0
A40: Pitch Adder | E40: =B24*D17 -> 0
A41: Extra Costs | E41: =SUM(E38:E40) -> 0
A43: General Labour | E43: =B24*'Costs & Prices'!B59 -> 0
A44: Battery Labour | E44: =C9*F9+C10*F10 -> 0
A45: Total Labour | E45: =SUM(E43:E44) -> 0
A47: Lead Gen | E47: ='Costs & Prices'!B60+B24*'Costs & Prices'!B61 -> 300
A48: Salary | E48: ='Costs & Prices'!B62 -> 100
A49: Commission (5%) | E49: =(E36+E45)*'Costs & Prices'!B63 -> 0
A50: Pre-sale | E50: =B24*'Costs & Prices'!B64 -> 0
A51: Total Acquisition | E51: =SUM(E47:E50) -> 400
A53: Fulfillment (PM+Design+Permit) | E53: ='Costs & Prices'!B65+'Costs & Prices'!B66+'Costs & Prices'!B67 -> 1850
A55: TOTAL COSTS | E55: =E36+E41+E45+E51+E53 -> 2250
A56: BASE PRICE (Costs x (1+Markup)) | E56: =E55*(1+D14) -> 3150
A57: AFTER ADDERS | E57: =E56+B20 -> 3150
A59: PE LEASE & FINAL PRICING
A60: System Type | B60: =IF(AND(B23>0,B25>0),"solar+battery",IF(B23>0,"solar",IF(B25>0,"battery","none"))) -> none
A61: Solar DC Qualified? | B61: =IF(B23=0,"No",IF(AND(IF(C5>0,VLOOKUP(B5,'Costs & Prices'!A3:D5,4,FALSE())="Yes",TRUE()),IF(C6>0,VLOOKUP(B6,'Costs & Prices'!A3:D5,4,FALSE())="Yes",TRUE())),"Yes","No")) -> No
A62: Battery DC Qualified? | B62: =IF(B25=0,"No",IF(AND(IF(C9>0,VLOOKUP(B9,'Costs & Prices'!A19:D20,4,FALSE())="Yes",TRUE()),IF(C10>0,VLOOKUP(B10,'Costs & Prices'!A19:D20,4,FALSE())="Yes",TRUE())),"Yes","No")) -> No
A63: Lease Factor Adjustment | B63: =IF(B18<>"Yes",0,IF(B60="solar+battery",IF(AND(B61="Yes",B62="Yes"),'Costs & Prices'!B73,IF(OR(B61="Yes",B62="Yes",B19="Yes"),0,'Costs & Prices'!B74)),IF(B60="solar",IF(B61="Yes",'Costs & Prices'!B73,IF(B19="Yes",0,'Costs & Prices'!B74)),IF(B60="battery",IF(B62="Yes",'Costs & Prices'!B73,IF(B19="Yes",0,'Costs & Prices'!B74)),0)))) -> 0
A64: Lease Factor | B64: ='Costs & Prices'!B72+B63 -> 1.4285714
A66: EPC Price (HubSpot Amount) | E66: =E57 -> 3150
A67: CUSTOMER PAYS | E67: =IF(B18="Yes",E66*(1-'Costs & Prices'!B75),E66) -> 3150
A68: PE Payment to PB | E68: =IF(B18="Yes",E66-(E66/B64),0) -> 0
A69: PE @ Inspection Complete (2/3) | E69: =E68*(2/3) -> 0
A70: PE @ Project Complete (1/3) | E70: =E68*(1/3) -> 0
A71: TOTAL PB REVENUE | E71: =IF(B18="Yes",E67+E68,E67) -> 3150
